naver/__init__.py
naver/find.py
naver/session.py
naverpaper-0.97.dist-info/METADATA
naverpaper-0.97.dist-info/WHEEL
naverpaper-0.97.dist-info/licenses/LICENSE
naverpaper-0.97.dist-info/RECORD
